{"name":"choose a product and it is displayed in the shopping cart successfully","id":"add-a-product-to-shopping-cart;choose-a-product-and-it-is-displayed-in-the-shopping-cart-successfully","testSteps":[{"number":1,"description":"Given that I open the browser at sauce lab page","duration":3701,"startTime":"2021-12-27T19:40:33.445-05:00[America/Bogota]","screenshots":[{"screenshot":"1257bec8dedb6a710d0115209b50a354bbeaab03bfd49f3d8870351dbf0cb424.png","timeStamp":1640652037146}],"result":"SUCCESS","precondition":false,"level":0,"children":[{"number":2,"description":"Go to saucedemo web page","duration":3118,"startTime":"2021-12-27T19:40:33.476-05:00[America/Bogota]","screenshots":[{"screenshot":"7430205a85ababa296f0b5d9e7ed004c2f8807bdb21d211ca455a772b28ecef1.png","timeStamp":1640652036594}],"result":"SUCCESS","precondition":false,"level":1},{"number":3,"description":"User enter credentials: standard_user, secret_sauce","duration":540,"startTime":"2021-12-27T19:40:36.594-05:00[America/Bogota]","screenshots":[{"screenshot":"7430205a85ababa296f0b5d9e7ed004c2f8807bdb21d211ca455a772b28ecef1.png","timeStamp":1640652036626},{"screenshot":"1257bec8dedb6a710d0115209b50a354bbeaab03bfd49f3d8870351dbf0cb424.png","timeStamp":1640652037134}],"result":"SUCCESS","precondition":false,"level":1}]},{"number":4,"description":"When I select any displayed result to go to the shopping cart","duration":352,"startTime":"2021-12-27T19:40:37.147-05:00[America/Bogota]","screenshots":[{"screenshot":"f12b48781c71c52a6974a545379b90951c43748bb3a72bf7e1a2a3835383bda3.png","timeStamp":1640652037499}],"result":"SUCCESS","precondition":false,"level":0,"children":[{"number":5,"description":"Choose random product","duration":188,"startTime":"2021-12-27T19:40:37.155-05:00[America/Bogota]","screenshots":[{"screenshot":"d9af58f008ebfd7fee04d680737d583f7a03f17be1a08c7f8d8f35e0ef01ae65.png","timeStamp":1640652037343}],"result":"SUCCESS","precondition":false,"level":1},{"number":6,"description":"Add to shopping cart","duration":156,"startTime":"2021-12-27T19:40:37.343-05:00[America/Bogota]","screenshots":[{"screenshot":"d9af58f008ebfd7fee04d680737d583f7a03f17be1a08c7f8d8f35e0ef01ae65.png","timeStamp":1640652037359},{"screenshot":"f12b48781c71c52a6974a545379b90951c43748bb3a72bf7e1a2a3835383bda3.png","timeStamp":1640652037499}],"result":"SUCCESS","precondition":false,"level":1}]},{"number":7,"description":"Then should the shopping cart show the product is not \"null\"","duration":6012,"startTime":"2021-12-27T19:40:37.518-05:00[America/Bogota]","screenshots":[{"screenshot":"fc4729151ddf09959bcbd9034e24fe47fb741f1f7fc7cdfef0f26010951a483d.png","timeStamp":1640652043530}],"result":"SUCCESS","precondition":false,"level":0,"children":[{"number":8,"description":"Go to cart page","duration":5846,"startTime":"2021-12-27T19:40:37.529-05:00[America/Bogota]","screenshots":[{"screenshot":"fc4729151ddf09959bcbd9034e24fe47fb741f1f7fc7cdfef0f26010951a483d.png","timeStamp":1640652043375}],"result":"SUCCESS","precondition":false,"level":1},{"number":9,"description":"Validate shopping cart","duration":140,"startTime":"2021-12-27T19:40:43.375-05:00[America/Bogota]","screenshots":[{"screenshot":"fc4729151ddf09959bcbd9034e24fe47fb741f1f7fc7cdfef0f26010951a483d.png","timeStamp":1640652043391},{"screenshot":"fc4729151ddf09959bcbd9034e24fe47fb741f1f7fc7cdfef0f26010951a483d.png","timeStamp":1640652043515}],"result":"SUCCESS","precondition":false,"level":1}]}],"userStory":{"id":"add-a-product-to-shopping-cart","storyName":"Add a product to shopping cart","displayName":"Add a product to shopping cart","path":"productToShoppingCart.feature","narrative":"  As a user I want to add a product to the cart","type":"feature"},"featureTag":{"name":"Add a product to shopping cart","type":"feature","displayName":"Add a product to shopping cart"},"title":"choose a product and it is displayed in the shopping cart successfully","description":"","tags":[{"name":"Add a product to shopping cart","type":"feature","displayName":"Add a product to shopping cart"},{"name":"productToShoppingCart","type":"tag","displayName":"productToShoppingCart"}],"startTime":"2021-12-27T19:40:33.445-05:00[America/Bogota]","duration":10085,"projectKey":"","sessionId":"832622cbbb3bfc30105ee750325049a3","driver":"chrome","isManualTestingUpToDate":false,"manual":false,"testSource":"Cucumber","result":"SUCCESS"}